ovos_bidirectional_translation_plugin/__init__.py
ovos_bidirectional_translation_plugin/version.py
ovos_bidirectional_translation_plugin-0.1.2.dist-info/LICENSE
ovos_bidirectional_translation_plugin-0.1.2.dist-info/METADATA
ovos_bidirectional_translation_plugin-0.1.2.dist-info/WHEEL
ovos_bidirectional_translation_plugin-0.1.2.dist-info/entry_points.txt
ovos_bidirectional_translation_plugin-0.1.2.dist-info/top_level.txt
ovos_bidirectional_translation_plugin-0.1.2.dist-info/zip-safe
ovos_bidirectional_translation_plugin-0.1.2.dist-info/RECORD
