Metadata-Version: 2.1
Name: ovos-bidirectional-translation-plugin
Version: 0.1.2
Summary: Bidirectional translation plugin to make OVOS understand any language
Home-page: https://github.com/OpenVoiceOS/ovos_bidirectional_translation_plugin
Author: jarbasAi
Author-email: jarbasai@mailfence.com
License: UNKNOWN
Keywords: OVOS plugin utterance transformer
Platform: UNKNOWN
